linter.py
main.py
manual_test.py
mcp_server.py
setup.py
test_mcp_integration.py
verify_server.py
mcp_testing_sensei-0.2.1.dist-info/METADATA
mcp_testing_sensei-0.2.1.dist-info/WHEEL
mcp_testing_sensei-0.2.1.dist-info/entry_points.txt
mcp_testing_sensei-0.2.1.dist-info/RECORD
