Metadata-Version: 2.3
Name: mcp-testing-sensei
Version: 0.2.1
Summary: An MCP server to guide agentic coding tools to use language agnostic testing principles.
Keywords: mcp,testing,linter,sensei,unit-testing
Author: Kourtni Marshall
Requires-Python: >=3.10
Classifier: Development Status :: 3 - Alpha
Classifier: Intended Audience :: Developers
Classifier: Programming Language :: Python :: 3
Classifier: Programming Language :: Python :: 3.10
Classifier: Programming Language :: Python :: 3.11
Classifier: Programming Language :: Python :: 3.12
Classifier: Programming Language :: Python :: 3.13
Requires-Dist: mcp (>=1.0.0,<2.0.0)
Project-URL: Homepage, https://github.com/kourtni/mcp-testing-sensei
Project-URL: Repository, https://github.com/kourtni/mcp-testing-sensei
